[
    {
        "className": "CI",
        "objectId": 3,
        "description": "n/a",
        "originalText": "endoscopeEyepiece",
        "translatedText": ""
    },
    {
        "className": "CI",
        "objectId": 4,
        "description": "n/a",
        "originalText": "Endoscope Eyepiece",
        "translatedText": ""
    },
    {
        "className": "CI",
        "objectId": 6,
        "description": "n/a",
        "originalText": "The eyepiece of an endoscope that can be used to attach to the end of an optical fiber to create some type of endoscopic device.",
        "translatedText": ""
    },
    {
        "className": "CI",
        "objectId": 7,
        "description": "n/a",
        "originalText": "Components.EndoscopeEyepiece",
        "translatedText": ""
    },
    {
        "className": "CSR",
        "objectId": 15,
        "description": "n/a",
        "originalText": "Electronics",
        "translatedText": ""
    }
]