[
    {
        "className": "OD",
        "objectId": 3,
        "description": "n/a",
        "originalText": "Oddity.CoreCityPlans",
        "translatedText": ""
    },
    {
        "className": "OD",
        "objectId": 4,
        "description": "n/a",
        "originalText": "Core City Plans",
        "translatedText": ""
    },
    {
        "className": "OD",
        "objectId": 6,
        "description": "n/a",
        "originalText": "Old and damaged Core City plans. Mostly illegible.",
        "translatedText": ""
    },
    {
        "className": "OD",
        "objectId": 7,
        "description": "n/a",
        "originalText": "Oddity.CoreCityPlans",
        "translatedText": ""
    }
]