[
    {
        "className": "CI",
        "objectId": 3,
        "description": "n/a",
        "originalText": "psiCrabHippocampus",
        "translatedText": ""
    },
    {
        "className": "CI",
        "objectId": 4,
        "description": "n/a",
        "originalText": "Psi Crab Hippocampus",
        "translatedText": ""
    },
    {
        "className": "CI",
        "objectId": 6,
        "description": "n/a",
        "originalText": "A part of the psi crab brain that contains some essential psionic chemicals.",
        "translatedText": ""
    },
    {
        "className": "CI",
        "objectId": 7,
        "description": "n/a",
        "originalText": "Components.PsiCrabHippocampus",
        "translatedText": ""
    },
    {
        "className": "CSR",
        "objectId": 15,
        "description": "n/a",
        "originalText": "Biology",
        "translatedText": ""
    },
    {
        "className": "P",
        "objectId": 16,
        "description": "n/a",
        "originalText": "Product",
        "translatedText": ""
    },
    {
        "className": "P",
        "objectId": 17,
        "description": "n/a",
        "originalText": "Xpbl\\PsiSomaticAgent",
        "translatedText": ""
    }
]