[
    {
        "classInfo": "(Q).SE:LT:0:Value",
        "objectId": 29,
        "description": "n/a",
        "originalText": "I lost all my money...",
        "translatedText": "",
        "ignore": false
    },
    {
        "classInfo": "(Q).SE:LT:0:Value",
        "objectId": 34,
        "description": "n/a",
        "originalText": "The Indestructible Avenger has been killed!",
        "translatedText": "",
        "ignore": false
    },
    {
        "classInfo": "(Q).SE:LT:0:Value",
        "objectId": 39,
        "description": "n/a",
        "originalText": "No! NO! NOOOOOO!",
        "translatedText": "",
        "ignore": false
    },
    {
        "classInfo": "(Q).SE:LT:0:Value",
        "objectId": 45,
        "description": "n/a",
        "originalText": "Damn it! Why did I bet on Dread Lord? Ugh!",
        "translatedText": "",
        "ignore": false
    },
    {
        "classInfo": "(Q).SE:LT:0:Value",
        "objectId": 50,
        "description": "n/a",
        "originalText": "That's it - I'm never betting again!",
        "translatedText": "",
        "ignore": false
    },
    {
        "classInfo": "(Q).SE:LT:0:Value",
        "objectId": 55,
        "description": "n/a",
        "originalText": "Betting is stupid!",
        "translatedText": "",
        "ignore": false
    },
    {
        "classInfo": "(BC).CIC:P",
        "objectId": 59,
        "description": "前後のテキストの状況を示すヒントになるかも",
        "originalText": "context.loc_cc_arenaFinished",
        "ignore": true,
        "translatedText": ""
    },
    {
        "jsonVersion": "0.3"
    }
]