[
    {
        "className": "DM",
        "objectId": 3,
        "description": "n/a",
        "originalText": "pb_rec",
        "translatedText": ""
    },
    {
        "className": "DM",
        "objectId": 4,
        "description": "n/a",
        "originalText": "",
        "translatedText": ""
    },
    {
        "className": "J",
        "objectId": 11,
        "description": "n/a",
        "originalText": "Start Element",
        "translatedText": ""
    },
    {
        "className": "A4",
        "objectId": 12,
        "description": "n/a",
        "originalText": "speaker",
        "translatedText": ""
    },
    {
        "className": "Q",
        "objectId": 28,
        "description": "n/a",
        "originalText": "What the hell is your problem, leave us alone!",
        "translatedText": ""
    },
    {
        "className": "Q",
        "objectId": 33,
        "description": "n/a",
        "originalText": "Not now, $(#man/woman)...",
        "translatedText": ""
    },
    {
        "className": "Q",
        "objectId": 38,
        "description": "n/a",
        "originalText": "Come on! Can't you see we're in the middle of something?",
        "translatedText": ""
    },
    {
        "className": "Q",
        "objectId": 43,
        "description": "n/a",
        "originalText": "Move aside, $(#man/woman). Let me train.",
        "translatedText": ""
    },
    {
        "className": "Q",
        "objectId": 48,
        "description": "n/a",
        "originalText": "::The recruit tries to ignore you.::",
        "translatedText": ""
    },
    {
        "className": "Q",
        "objectId": 53,
        "description": "n/a",
        "originalText": "Darn it, what do you want now?",
        "translatedText": ""
    }
]