[
    {
        "className": "DM",
        "objectId": 3,
        "description": "n/a",
        "originalText": "dun_lowLevelBunker4_Ryl",
        "translatedText": ""
    },
    {
        "className": "DM",
        "objectId": 4,
        "description": "n/a",
        "originalText": "",
        "translatedText": ""
    },
    {
        "className": "J",
        "objectId": 30,
        "description": "n/a",
        "originalText": "Start Element",
        "translatedText": ""
    },
    {
        "className": "A4",
        "objectId": 31,
        "description": "n/a",
        "originalText": "ryl",
        "translatedText": ""
    },
    {
        "className": "Q",
        "objectId": 46,
        "description": "n/a",
        "originalText": "We were planning for so many adventures and now, it's all gone.",
        "translatedText": ""
    },
    {
        "className": "Q",
        "objectId": 52,
        "description": "n/a",
        "originalText": "I'll never forget what we've been through.",
        "translatedText": ""
    },
    {
        "className": "Q",
        "objectId": 59,
        "description": "n/a",
        "originalText": "We would've been toast without you. Thank you.",
        "translatedText": ""
    },
    {
        "className": "Q",
        "objectId": 65,
        "description": "n/a",
        "originalText": "We, ugh... I... I have failed.",
        "translatedText": ""
    },
    {
        "className": "Q",
        "objectId": 71,
        "description": "n/a",
        "originalText": "Get ready. They're coming!",
        "translatedText": ""
    },
    {
        "className": "Q",
        "objectId": 76,
        "description": "n/a",
        "originalText": "With or without you.",
        "translatedText": ""
    },
    {
        "className": "PIIAWPC",
        "objectId": 79,
        "description": "n/a",
        "originalText": "cc-res",
        "translatedText": ""
    },
    {
        "className": "Q",
        "objectId": 82,
        "description": "n/a",
        "originalText": "We are considering to settle around here for a while. Not sure if we are up to the place such as this one, though.",
        "translatedText": ""
    },
    {
        "className": "Q",
        "objectId": 87,
        "description": "n/a",
        "originalText": "That green sofa right there. Ahh.. I can only imagine.",
        "translatedText": ""
    },
    {
        "className": "Q",
        "objectId": 92,
        "description": "n/a",
        "originalText": "Hmm, how about... ah, I can't make up my mind.",
        "translatedText": ""
    },
    {
        "className": "SBFV",
        "objectId": 103,
        "description": "n/a",
        "originalText": "context.loc_dun_llb4_diedRyl_helped",
        "translatedText": ""
    },
    {
        "className": "BC",
        "objectId": 104,
        "description": "n/a",
        "originalText": "context.npc_dun_llb4_diedrick_dead",
        "translatedText": ""
    },
    {
        "className": "ICC",
        "objectId": 113,
        "description": "n/a",
        "originalText": "context.dun_llb4_enemyCount",
        "translatedText": ""
    }
]