[
    {
        "className": "WI",
        "objectId": 4,
        "description": "n/a",
        "originalText": "rustMakerKnife",
        "translatedText": ""
    },
    {
        "className": "WI",
        "objectId": 5,
        "description": "n/a",
        "originalText": "Rust Maker",
        "translatedText": ""
    },
    {
        "className": "WI",
        "objectId": 7,
        "description": "n/a",
        "originalText": "This spear tip seems to have spent enough time lodged inside a Sea Wyrm to get infused with it's rusting acid. It might serve as a rather unwieldy knife, or you could try and repair it.",
        "translatedText": ""
    },
    {
        "className": "WI",
        "objectId": 8,
        "description": "n/a",
        "originalText": "xpbl_Weapons.223",
        "translatedText": ""
    },
    {
        "className": "WI",
        "objectId": 22,
        "description": "n/a",
        "originalText": "k",
        "translatedText": ""
    },
    {
        "className": "WI",
        "objectId": 26,
        "description": "n/a",
        "originalText": "AcidFizz",
        "translatedText": ""
    },
    {
        "className": "CR",
        "objectId": 35,
        "description": "n/a",
        "originalText": "startInterfacing",
        "translatedText": ""
    },
    {
        "className": "HER",
        "objectId": 36,
        "description": "n/a",
        "originalText": "rustingAcidSplash",
        "translatedText": ""
    },
    {
        "className": "P",
        "objectId": 38,
        "description": "n/a",
        "originalText": "InterfaceActorId",
        "translatedText": ""
    },
    {
        "className": "P",
        "objectId": 39,
        "description": "n/a",
        "originalText": "interface",
        "translatedText": ""
    }
]