[
    {
        "className": "CI",
        "objectId": 3,
        "description": "n/a",
        "originalText": "Crossbow Parts: Hurricane",
        "translatedText": ""
    },
    {
        "className": "CI",
        "objectId": 5,
        "description": "n/a",
        "originalText": "With an appropriate blueprint, these parts can be used to create a Hurricane type crossbow.",
        "translatedText": ""
    },
    {
        "className": "CI",
        "objectId": 6,
        "description": "n/a",
        "originalText": "crossbow.2.parts",
        "translatedText": ""
    },
    {
        "className": "CSR",
        "objectId": 15,
        "description": "n/a",
        "originalText": "Mechanics",
        "translatedText": ""
    },
    {
        "className": "P",
        "objectId": 16,
        "description": "n/a",
        "originalText": "DamageSpread",
        "translatedText": ""
    },
    {
        "className": "P",
        "objectId": 18,
        "description": "n/a",
        "originalText": "Name",
        "translatedText": ""
    },
    {
        "className": "P",
        "objectId": 19,
        "description": "n/a",
        "originalText": "Hurricane",
        "translatedText": ""
    }
]