[
    {
        "classInfo": ".J.CE:N",
        "objectId": 12,
        "description": "n/a",
        "originalText": "Start Element",
        "translatedText": ""
    },
    {
        "classInfo": ".A4.A4:N",
        "objectId": 13,
        "description": "n/a",
        "originalText": "speaker",
        "translatedText": ""
    },
    {
        "classInfo": ".A4.A4:N",
        "objectId": 14,
        "description": "n/a",
        "originalText": "player",
        "translatedText": ""
    },
    {
        "classInfo": ".Q.SE:LT:0:Value",
        "objectId": 32,
        "description": "n/a",
        "originalText": "Finally - Core City!",
        "translatedText": ""
    },
    {
        "classInfo": ".Q.SE:LT:0:Value",
        "objectId": 37,
        "description": "n/a",
        "originalText": "Hey, do you know where to find this Core City Housing Corporation, if I said that one correctly?",
        "translatedText": ""
    },
    {
        "classInfo": ".Q.SE:LT:0:Value",
        "objectId": 42,
        "description": "n/a",
        "originalText": "Is this your first time in Core City?",
        "translatedText": ""
    },
    {
        "classInfo": ".Q.SE:LT:0:Value",
        "objectId": 48,
        "description": "n/a",
        "originalText": "I'm just glad my train wasn't blown up by those evil Faceless!",
        "translatedText": ""
    },
    {
        "classInfo": ".Q.SE:LT:0:Value",
        "objectId": 53,
        "description": "n/a",
        "originalText": "This place looks promising.",
        "translatedText": ""
    },
    {
        "classInfo": ".Q.SE:LT:0:Value",
        "objectId": 59,
        "description": "n/a",
        "originalText": "I gotta visit the Arena soon...",
        "translatedText": ""
    },
    {
        "classInfo": ".Q.SE:LT:0:Value",
        "objectId": 64,
        "description": "n/a",
        "originalText": "Hello, stranger!",
        "translatedText": ""
    },
    {
        "classInfo": ".Q.SE:LT:0:Value",
        "objectId": 69,
        "description": "n/a",
        "originalText": "I could see myself living here. Yeah, not bad at all.",
        "translatedText": ""
    },
    {
        "classInfo": ".Q.SE:LT:0:Value",
        "objectId": 75,
        "description": "n/a",
        "originalText": "This place feels safe now that the Faceless have been driven of. Safe-er, 'scuse me.",
        "translatedText": ""
    },
    {
        "classInfo": ".BC.CIC:P",
        "objectId": 79,
        "description": "n/a",
        "originalText": "context.loc_cc_facelessRetreated",
        "translatedText": ""
    },
    {
        "classInfo": ".SBFV.SFVA:P",
        "objectId": 81,
        "description": "n/a",
        "originalText": "context.loc_cc_knowArena",
        "translatedText": ""
    },
    {
        "classInfo": ".BC.CIC:P",
        "objectId": 82,
        "description": "n/a",
        "originalText": "context.loc_cc_facelessRetreated",
        "translatedText": ""
    },
    {
        "jsonVersion": "0.2"
    }
]