[
    {
        "className": "HI",
        "objectId": 3,
        "description": "n/a",
        "originalText": "deathsGrin",
        "translatedText": ""
    },
    {
        "className": "HI",
        "objectId": 4,
        "description": "n/a",
        "originalText": "Death's Grin",
        "translatedText": ""
    },
    {
        "className": "HI",
        "objectId": 6,
        "description": "n/a",
        "originalText": "A menacing cloth bandana depicting a set of human teeth. The cloth from which the teeth are weaved appears to be fluorescent.",
        "translatedText": ""
    },
    {
        "className": "HI",
        "objectId": 7,
        "description": "n/a",
        "originalText": "xpbl_Armors.12",
        "translatedText": ""
    },
    {
        "className": "MSFE1",
        "objectId": 16,
        "description": "n/a",
        "originalText": "Intimidation",
        "translatedText": ""
    }
]